harmoniums/__init__.py
harmoniums/base.py
harmoniums/binary.py
harmoniums/const.py
harmoniums/distributions.py
harmoniums/functional_math.py
harmoniums/gamma.py
harmoniums/gamma_censor.py
harmoniums/gaussian.py
harmoniums/log_metrics.py
harmoniums/samplers.py
harmoniums/survival.py
harmoniums/tensorboard_logging.py
harmoniums/utils.py
harmoniums/views.py
harmoniums/wrappers.py
harmoniums/datasets/__init__.py
harmoniums/datasets/nvalt11.csv
harmoniums/datasets/nvalt8.csv
harmoniums-0.1.2.dist-info/LICENSE.txt
harmoniums-0.1.2.dist-info/METADATA
harmoniums-0.1.2.dist-info/WHEEL
harmoniums-0.1.2.dist-info/top_level.txt
harmoniums-0.1.2.dist-info/RECORD
